bridge/__init__.py
bridge/baseapi.py
bridge/client.py
bridge/exceptions.py
bridge/entities/__init__.py
bridge/entities/account.py
bridge/entities/bank.py
bridge/entities/item.py
bridge/entities/transaction.py
bridge/entities/user.py
bankin_bridge-0.1.0a4.dist-info/LICENSE
bankin_bridge-0.1.0a4.dist-info/METADATA
bankin_bridge-0.1.0a4.dist-info/WHEEL
bankin_bridge-0.1.0a4.dist-info/top_level.txt
bankin_bridge-0.1.0a4.dist-info/RECORD
