Metadata-Version: 2.1
Name: bankin-bridge
Version: 0.1.0a4
Summary: A Python module for communicating with the Bridgeapi.io API.
Home-page: https://github.com/impak-finance/bankin-bridge-python
Author: impak Finance
Author-email: tech@impakfinance.com
License: MIT
Keywords: bankin bankin-bridge bridge bank financial data institution
Platform: UNKNOWN
Classifier: Development Status :: 3 - Alpha
Classifier: Environment :: Web Environment
Classifier: Intended Audience :: Developers
Classifier: License :: OSI Approved :: MIT License
Classifier: Natural Language :: English
Classifier: Programming Language :: Python
Classifier: Programming Language :: Python :: 3
Classifier: Programming Language :: Python :: 3.4
Classifier: Programming Language :: Python :: 3.5
Classifier: Programming Language :: Python :: 3.6
Classifier: Programming Language :: Python :: 3.7
Requires-Dist: requests (>=2.0)
